fill_image_resize/__init__.py
fill_image_resize/resizer.py
fill_image_resize-1.2.0.dist-info/LICENSE
fill_image_resize-1.2.0.dist-info/METADATA
fill_image_resize-1.2.0.dist-info/WHEEL
fill_image_resize-1.2.0.dist-info/top_level.txt
fill_image_resize-1.2.0.dist-info/RECORD
