Metadata-Version: 2.1
Name: fill-image-resize
Version: 1.2.0
Summary: Package provides function for rather neat image resizing (like Fill resize in Figma)
Home-page: https://github.com/d0ctr/fill-image-resize
Author: Danila Vasilev
Author-email: mail@vasilev.ml
License: UNKNOWN
Project-URL: Bug Tracker, https://github.com/d0ctr/fill-image-resize/issues
Platform: UNKNOWN
Classifier: Programming Language :: Python :: 3
Classifier: License :: OSI Approved :: GNU General Public License v3 (GPLv3)
Classifier: Operating System :: OS Independent
Requires-Python: >=3.6
License-File: LICENSE
Requires-Dist: Pillow (>=7.0.0)
